myelectricaldatapy/__init__.py
myelectricaldatapy/analytics.py
myelectricaldatapy/auth.py
myelectricaldatapy/const.py
myelectricaldatapy/exceptions.py
myelectricaldatapy/myelectricaldata.py
myelectricaldatapy/mypdl.py
myelectricaldatapy/py.typed
myelectricaldatapy-2.2.5.dist-info/licenses/LICENSE
myelectricaldatapy-2.2.5.dist-info/METADATA
myelectricaldatapy-2.2.5.dist-info/WHEEL
myelectricaldatapy-2.2.5.dist-info/top_level.txt
myelectricaldatapy-2.2.5.dist-info/RECORD
