Metadata-Version: 2.4
Name: myelectricaldatapy
Version: 2.2.5
Summary: Fetch Linky data from myelectricaldata.fr
Author-email: Cyr-ius <cyr-ius@ipocus.net>
License: GPL-3
Project-URL: Homepage, https://github.com/cyr-ius/myelectricaldatapy
Keywords: enedis,linky,async,myelectricaldata
Classifier: Programming Language :: Python
Classifier: Development Status :: 5 - Production/Stable
Classifier: License :: OSI Approved :: GNU General Public License v3 or later (GPLv3+)
Classifier: Programming Language :: Python :: 3
Classifier: Programming Language :: Python :: 3.10
Classifier: Programming Language :: Python :: 3.11
Classifier: Framework :: AsyncIO
Classifier: Intended Audience :: Developers
Classifier: Intended Audience :: System Administrators
Classifier: Topic :: Home Automation
Requires-Python: >=3.10.0
License-File: LICENSE
Requires-Dist: aiohttp>=3.8.1
Requires-Dist: pandas>=2.0.2
Requires-Dist: voluptuous>=0.13.1
Dynamic: license-file
